terra_layer/__init__.py
terra_layer/apps.py
terra_layer/models.py
terra_layer/permissions.py
terra_layer/serializers.py
terra_layer/sources_serializers.py
terra_layer/utils.py
terra_layer/migrations/0001_initial.py
terra_layer/migrations/0002_auto_20190524_1151.py
terra_layer/migrations/0003_auto_20190528_1629.py
terra_layer/migrations/0004_auto_20190605_1638.py
terra_layer/migrations/0005_auto_20190606_1635.py
terra_layer/migrations/0006_auto_20190607_1151.py
terra_layer/migrations/0007_auto_20190611_1110.py
terra_layer/migrations/0008_auto_20190611_1323.py
terra_layer/migrations/0009_auto_20190612_1020.py
terra_layer/migrations/0010_auto_20190612_1718.py
terra_layer/migrations/0011_auto_20190612_1721.py
terra_layer/migrations/0012_auto_20190618_1500.py
terra_layer/migrations/0013_auto_20190620_1455.py
terra_layer/migrations/0014_filterfield_label.py
terra_layer/migrations/0015_remove_filterfield_filter_type.py
terra_layer/migrations/0016_auto_20190625_1436.py
terra_layer/migrations/0017_remove_layer_legend_enable.py
terra_layer/migrations/0018_auto_20190626_0956.py
terra_layer/migrations/0020_sublayer.py
terra_layer/migrations/0021_auto_20190627_1513.py
terra_layer/migrations/0022_auto_20190628_0928.py
terra_layer/migrations/0023_layer_interactions.py
terra_layer/migrations/0024_customstyle_interactions.py
terra_layer/migrations/0025_auto_20190715_1425.py
terra_layer/migrations/0025_layer_settings.py
terra_layer/migrations/0026_layer_group.py
terra_layer/migrations/0027_auto_20190715_1631.py
terra_layer/migrations/0028_layergroup_exclusive.py
terra_layer/migrations/0029_auto_20190716_1643.py
terra_layer/migrations/0030_layergroup_order.py
terra_layer/migrations/0031_auto_20190718_1601.py
terra_layer/migrations/0032_auto_20190718_1742.py
terra_layer/migrations/0033_layergroup_settings.py
terra_layer/migrations/0034_layer_in_tree.py
terra_layer/migrations/0035_auto_20190723_1418.py
terra_layer/migrations/0036_auto_20190731_1848.py
terra_layer-0.3.1.dist-info/LICENCE.md
terra_layer-0.3.1.dist-info/METADATA
terra_layer-0.3.1.dist-info/WHEEL
terra_layer-0.3.1.dist-info/top_level.txt
terra_layer-0.3.1.dist-info/RECORD
