Metadata-Version: 2.1
Name: terra-layer
Version: 0.3.1
Summary: Geographic data visualizer backend for terra-visu
Home-page: https://github.com/Terralego/terra-layer.git
Author: Makina Corpus
Author-email: terralego-pypi@makina-corpus.com
License: UNKNOWN
Platform: UNKNOWN
Classifier: Environment :: Web Environment
Classifier: Framework :: Django
Classifier: Intended Audience :: Developers
Classifier: Topic :: Internet :: WWW/HTTP
Classifier: Topic :: Internet :: WWW/HTTP :: Dynamic Content
Classifier: License :: OSI Approved :: MIT License
Classifier: Natural Language :: English
Classifier: Operating System :: OS Independent
Classifier: Programming Language :: Python
Classifier: Programming Language :: Python :: 3.6
Classifier: Programming Language :: Python :: 3.7
Requires-Dist: Django (>=2.2.7)
Requires-Dist: djangorestframework (<3.9,>=3.8)
Requires-Dist: django-geosource (>=0.3)
Requires-Dist: django-geostore (>=0.3.11)
Requires-Dist: django-terra-accounts (>=0.3.6)
Requires-Dist: terra-common (>=0.3)
Provides-Extra: dev
Requires-Dist: factory-boy ; extra == 'dev'
Requires-Dist: flake8 ; extra == 'dev'
Requires-Dist: coverage ; extra == 'dev'
